boldi/_proc_version.py
boldi/proc.py
boldi_proc-0.9.7.dist-info/METADATA
boldi_proc-0.9.7.dist-info/WHEEL
boldi_proc-0.9.7.dist-info/RECORD
