Metadata-Version: 2.4
Name: boldi-proc
Version: 0.9.7
Summary: boldi.proc part of Boldi's Python libraries
Author-email: Boldizsár Palotás <boldizsar.palotas@gmail.com>
License: MIT
Requires-Python: >=3.12
Requires-Dist: typing-extensions
